MANIFEST.in
README.rst
setup.py
src/sentry_bitbucket/__init__.py
src/sentry_bitbucket/models.py
src/sentry_bitbucket/plugin.py
src/sentry_bitbucket.egg-info/PKG-INFO
src/sentry_bitbucket.egg-info/SOURCES.txt
src/sentry_bitbucket.egg-info/dependency_links.txt
src/sentry_bitbucket.egg-info/entry_points.txt
src/sentry_bitbucket.egg-info/not-zip-safe
src/sentry_bitbucket.egg-info/requires.txt
src/sentry_bitbucket.egg-info/top_level.txt