Metadata-Version: 1.1
Name: sentry-bitbucket
Version: 0.1.5
Summary: A Sentry extension which integrates with Bitbucket.
Home-page: https://github.com/neilalbrock/sentry-bitbucket
Author: Neil Albrock
Author-email: neil@atomised.coop
License: BSD
Platform: UNKNOWN
Classifier: Framework :: Django
Classifier: Intended Audience :: Developers
Classifier: Intended Audience :: System Administrators
Classifier: Operating System :: OS Independent
Classifier: Topic :: Software Development
